django_plugin_debug_toolbar/__init__.py
django_plugin_debug_toolbar-0.1.1.dist-info/WHEEL
django_plugin_debug_toolbar-0.1.1.dist-info/entry_points.txt
django_plugin_debug_toolbar-0.1.1.dist-info/METADATA
django_plugin_debug_toolbar-0.1.1.dist-info/RECORD
