Metadata-Version: 2.3
Name: django-plugin-debug-toolbar
Version: 0.1.1
Summary: Django plugin wrapping django-debug-toolbar
Author: Joel Sleppy
Author-email: Joel Sleppy <joel@sleppytech.com>
License: Apache-2.0
Classifier: License :: OSI Approved :: Apache Software License
Requires-Dist: django
Requires-Dist: djp>=0.3.1
Requires-Dist: django-debug-toolbar==6.*
